muoblpbindings/__init__.py
muoblpbindings/__init__.pyi
muoblpbindings/muoblpbindings.cpython-313-x86_64-linux-gnu.so
muoblpbindings-0.0.16.dist-info/METADATA
muoblpbindings-0.0.16.dist-info/WHEEL
muoblpbindings-0.0.16.dist-info/RECORD
