Metadata-Version: 2.2
Name: muoblpbindings
Version: 0.0.16
Author-Email: Piotr Skowron <p.skowron@mimuw.edu.pl>, Jan Sznajd <j.sznajd@uw.edu.pl>
Requires-Python: >=3.11
